sdcvalidator/__init__.py
sdcvalidator/_limits.py
sdcvalidator/aliases.py
sdcvalidator/arguments.py
sdcvalidator/cli.py
sdcvalidator/dataobjects.py
sdcvalidator/documents.py
sdcvalidator/exceptions.py
sdcvalidator/exports.py
sdcvalidator/limits.py
sdcvalidator/loaders.py
sdcvalidator/locations.py
sdcvalidator/names.py
sdcvalidator/namespaces.py
sdcvalidator/py.typed
sdcvalidator/settings.py
sdcvalidator/translation.py
sdcvalidator/converters/__init__.py
sdcvalidator/converters/abdera.py
sdcvalidator/converters/badgerfish.py
sdcvalidator/converters/base.py
sdcvalidator/converters/columnar.py
sdcvalidator/converters/gdata.py
sdcvalidator/converters/jsonml.py
sdcvalidator/converters/parker.py
sdcvalidator/converters/unordered.py
sdcvalidator/core/__init__.py
sdcvalidator/core/assertions.py
sdcvalidator/core/attributes.py
sdcvalidator/core/builders.py
sdcvalidator/core/builtins.py
sdcvalidator/core/complex_types.py
sdcvalidator/core/elements.py
sdcvalidator/core/exceptions.py
sdcvalidator/core/facets.py
sdcvalidator/core/groups.py
sdcvalidator/core/helpers.py
sdcvalidator/core/identities.py
sdcvalidator/core/models.py
sdcvalidator/core/notations.py
sdcvalidator/core/particles.py
sdcvalidator/core/schemas.py
sdcvalidator/core/simple_types.py
sdcvalidator/core/validation.py
sdcvalidator/core/wildcards.py
sdcvalidator/core/xsd_globals.py
sdcvalidator/core/xsdbase.py
sdcvalidator/extras/__init__.py
sdcvalidator/extras/codegen.py
sdcvalidator/extras/wsdl.py
sdcvalidator/extras/templates/python/bindings.py.jinja
sdcvalidator/extras/templates/python/sample.py.jinja
sdcvalidator/locale/en/LC_MESSAGES/xmlschema.mo
sdcvalidator/locale/en/LC_MESSAGES/xmlschema.po
sdcvalidator/locale/it/LC_MESSAGES/xmlschema.mo
sdcvalidator/locale/it/LC_MESSAGES/xmlschema.po
sdcvalidator/locale/pl/LC_MESSAGES/xmlschema.mo
sdcvalidator/locale/pl/LC_MESSAGES/xmlschema.po
sdcvalidator/locale/ru/LC_MESSAGES/xmlschema.mo
sdcvalidator/locale/ru/LC_MESSAGES/xmlschema.po
sdcvalidator/resources/__init__.py
sdcvalidator-4.0.6.dist-info/licenses/LICENSE
sdcvalidator-4.0.6.dist-info/METADATA
sdcvalidator-4.0.6.dist-info/WHEEL
sdcvalidator-4.0.6.dist-info/entry_points.txt
sdcvalidator-4.0.6.dist-info/top_level.txt
sdcvalidator-4.0.6.dist-info/RECORD
