Metadata-Version: 2.4
Name: sdcvalidator
Version: 4.0.6
Summary: SDC4 XML validation with ExceptionalValue recovery
Author: Axius-SDC, Inc.
Maintainer-email: Tim Cook <contact@axius-sdc.com>
License-Expression: MIT
Project-URL: Homepage, https://github.com/Axius-SDC/sdcvalidator
Project-URL: Repository, https://github.com/Axius-SDC/sdcvalidator
Project-URL: Issues, https://github.com/Axius-SDC/sdcvalidator/issues
Classifier: Development Status :: 5 - Production/Stable
Classifier: Intended Audience :: Developers
Classifier: Intended Audience :: Information Technology
Classifier: Intended Audience :: Science/Research
Classifier: Operating System :: OS Independent
Classifier: Programming Language :: Python
Classifier: Programming Language :: Python :: 3
Classifier: Programming Language :: Python :: 3 :: Only
Classifier: Programming Language :: Python :: 3.9
Classifier: Programming Language :: Python :: 3.10
Classifier: Programming Language :: Python :: 3.11
Classifier: Programming Language :: Python :: 3.12
Classifier: Programming Language :: Python :: 3.13
Classifier: Programming Language :: Python :: 3.14
Classifier: Programming Language :: Python :: Implementation :: CPython
Classifier: Programming Language :: Python :: Implementation :: PyPy
Classifier: Topic :: Software Development :: Libraries
Classifier: Topic :: Text Processing :: Markup :: XML
Requires-Python: >=3.9
License-File: LICENSE
Requires-Dist: elementpath<6.0.0,>=5.0.1
Provides-Extra: codegen
Requires-Dist: jinja2; extra == "codegen"
Provides-Extra: dev
Requires-Dist: coverage; extra == "dev"
Requires-Dist: flake8; extra == "dev"
Requires-Dist: lxml; extra == "dev"
Requires-Dist: lxml-stubs; extra == "dev"
Requires-Dist: mypy; extra == "dev"
Requires-Dist: psutil; extra == "dev"
Requires-Dist: tox; extra == "dev"
Requires-Dist: xmlschema[docs]; extra == "dev"
Provides-Extra: docs
Requires-Dist: jinja2; extra == "docs"
Requires-Dist: sphinx; extra == "docs"
Requires-Dist: sphinx_rtd_theme; extra == "docs"
Dynamic: license-file
